byted_overpass_ecom_knowledege_graph_rec_mm_pairwise_service/__init__.py
byted_overpass_ecom_knowledege_graph_rec_mm_pairwise_service-0.0.1.dist-info/METADATA
byted_overpass_ecom_knowledege_graph_rec_mm_pairwise_service-0.0.1.dist-info/WHEEL
byted_overpass_ecom_knowledege_graph_rec_mm_pairwise_service-0.0.1.dist-info/top_level.txt
byted_overpass_ecom_knowledege_graph_rec_mm_pairwise_service-0.0.1.dist-info/RECORD
